golem_py/__init__.py
golem_py/__main__.py
golem_py/cli/__init__.py
golem_py/cli/cli.py
golem_py/cli/utils.py
golem_py/core/__init__.py
golem_py/core/activity_api/__init__.py
golem_py/core/activity_api/commands.py
golem_py/core/activity_api/events.py
golem_py/core/activity_api/exceptions.py
golem_py/core/activity_api/pipeline.py
golem_py/core/activity_api/resources/__init__.py
golem_py/core/activity_api/resources/activity.py
golem_py/core/activity_api/resources/pooling_batch.py
golem_py/core/events/__init__.py
golem_py/core/events/event.py
golem_py/core/events/event_bus.py
golem_py/core/events/event_filters.py
golem_py/core/exceptions.py
golem_py/core/golem_node/__init__.py
golem_py/core/golem_node/events.py
golem_py/core/golem_node/golem_node.py
golem_py/core/market_api/__init__.py
golem_py/core/market_api/exceptions.py
golem_py/core/market_api/pipeline.py
golem_py/core/market_api/resources/__init__.py
golem_py/core/market_api/resources/agreement.py
golem_py/core/market_api/resources/demand/__init__.py
golem_py/core/market_api/resources/demand/demand.py
golem_py/core/market_api/resources/demand/demand_builder.py
golem_py/core/market_api/resources/demand/demand_offer_base/__init__.py
golem_py/core/market_api/resources/demand/demand_offer_base/defaults.py
golem_py/core/market_api/resources/demand/demand_offer_base/exceptions.py
golem_py/core/market_api/resources/demand/demand_offer_base/model.py
golem_py/core/market_api/resources/demand/demand_offer_base/payload/__init__.py
golem_py/core/market_api/resources/demand/demand_offer_base/payload/base.py
golem_py/core/market_api/resources/demand/demand_offer_base/payload/vm.py
golem_py/core/market_api/resources/proposal.py
golem_py/core/network_api/__init__.py
golem_py/core/network_api/exceptions.py
golem_py/core/network_api/resources/__init__.py
golem_py/core/network_api/resources/network.py
golem_py/core/payment_api/__init__.py
golem_py/core/payment_api/exceptions.py
golem_py/core/payment_api/resources/__init__.py
golem_py-0.1.0.dist-info/METADATA
golem_py-0.1.0.dist-info/WHEEL
golem_py-0.1.0.dist-info/LICENSE
golem_py-0.1.0.dist-info/RECORD
